MANIFEST.in
README.rst
setup.py
bchmemo/__init__.py
bchmemo/memo.py
bchmemo/memouser.py
bchmemo.egg-info/PKG-INFO
bchmemo.egg-info/SOURCES.txt
bchmemo.egg-info/dependency_links.txt
bchmemo.egg-info/requires.txt
bchmemo.egg-info/top_level.txt
bchmemo/bitcash_modified/__init__.py
bchmemo/bitcash_modified/services.py
bchmemo/bitcash_modified/transaction.py