Metadata-Version: 1.1
Name: bchmemo
Version: 0.0.2
Summary: A python package for memo. Memo is an on-chain social network built on Bitcoin Cash
Home-page: https://github.com/remem9527/memo
Author: remem9527
Author-email: wszd163@163.com
License: MIT
Keywords: bitcoincash,social network,memo,on-chain data,OP_RETURN
Platform: UNKNOWN
Classifier: Intended Audience :: Developers
Classifier: Intended Audience :: End Users/Desktop
Classifier: License :: OSI Approved :: MIT License
Classifier: Natural Language :: English
Classifier: Operating System :: OS Independent
Classifier: Programming Language :: Python :: 3.6
Classifier: Programming Language :: Python :: Implementation :: CPython
Classifier: Programming Language :: Python :: Implementation :: PyPy
